superduperdb/__init__.py
superduperdb/py.typed
superduperdb-0.2.2.dist-info/LICENSE
superduperdb-0.2.2.dist-info/METADATA
superduperdb-0.2.2.dist-info/WHEEL
superduperdb-0.2.2.dist-info/top_level.txt
superduperdb-0.2.2.dist-info/RECORD
