Metadata-Version: 2.1
Name: superduperdb
Version: 0.2.2
Summary: 🔮 Bring AI to your favourite database 🔮
Maintainer-email: "SuperDuperDB, Inc." <opensource@superduperdb.com>
License: 
Project-URL: homepage, https://www.superduperdb.com/
Project-URL: documentation, https://docs.superduperdb.com
Project-URL: source, https://github.com/SuperDuperDB/superduperdb/
Keywords: databases,mongodb,data-science,machine-learning,mlops,vector-database,ai
Classifier: Development Status :: 3 - Alpha
Classifier: Environment :: GPU :: NVIDIA CUDA
Classifier: License :: OSI Approved :: Apache Software License
Classifier: Operating System :: OS Independent
Classifier: Programming Language :: Python :: 3.10
Classifier: Programming Language :: Python :: 3.11
Classifier: Programming Language :: Python :: Implementation :: CPython
Classifier: Topic :: Database
Classifier: Topic :: Scientific/Engineering :: Artificial Intelligence
Classifier: Topic :: Software Development :: Libraries :: Python Modules
Classifier: Typing :: Typed
Requires-Python: >=3.10
License-File: LICENSE
